README.rst
pollination.zip
screenshot01.png
setup.py
docs/HISTORY.txt
docs/INSTALL.txt
docs/LICENSE.GPL
docs/LICENSE.txt
plonetheme/__init__.py
plonetheme.pollination.egg-info/PKG-INFO
plonetheme.pollination.egg-info/SOURCES.txt
plonetheme.pollination.egg-info/dependency_links.txt
plonetheme.pollination.egg-info/entry_points.txt
plonetheme.pollination.egg-info/namespace_packages.txt
plonetheme.pollination.egg-info/not-zip-safe
plonetheme.pollination.egg-info/requires.txt
plonetheme.pollination.egg-info/top_level.txt
plonetheme/pollination/__init__.py
plonetheme/pollination/configure.zcml
plonetheme/pollination/profiles/default/metadata.xml
plonetheme/pollination/profiles/default/theme.xml
plonetheme/pollination/static/index.html
plonetheme/pollination/static/license.txt
plonetheme/pollination/static/manifest.cfg
plonetheme/pollination/static/rules-standard.xml
plonetheme/pollination/static/rules.xml
plonetheme/pollination/static/css/public.css
plonetheme/pollination/static/css/style.css
plonetheme/pollination/static/images/img01.jpg
plonetheme/pollination/static/images/img02.jpg
plonetheme/pollination/static/images/img03.jpg
plonetheme/pollination/static/images/img04.jpg
plonetheme/pollination/static/images/img05.jpg
plonetheme/pollination/static/images/img06.jpg