Metadata-Version: 1.0
Name: plonetheme.pollination
Version: 0.1
Summary: Pollination Theme
Home-page: http://svn.plone.org/svn/collective/plonetheme.pollination
Author: Irene Capatti
Author-email: irene.capatti@redturtle.it
License: GPL
Keywords: web zope plone theme diazo
Platform: UNKNOWN
Classifier: Framework :: Plone
Classifier: Programming Language :: Python
